<?xml version="1.0" encoding="utf-8" ?>
<dwsync>
<file name="basexml.php" server="ftp.amarca.net/amarca_management/" local="128913922820000000" remote="129236229000000000" />
<file name="commands.php" server="ftp.amarca.net/amarca_management/" local="129147966680000000" remote="129236229000000000" />
<file name="config.php" server="ftp.amarca.net/amarca_management/" local="129350188567656250" remote="129350189400000000" />
<file name="connector.php" server="ftp.amarca.net/amarca_management/" local="128765405000000000" remote="129236229000000000" />
<file name="io.php" server="ftp.amarca.net/amarca_management/" local="129147967380000000" remote="129236229000000000" />
<file name="phpcompat.php" server="ftp.amarca.net/amarca_management/" local="128479231260000000" remote="129236229000000000" />
<file name="upload.php" server="ftp.amarca.net/amarca_management/" local="129147966180000000" remote="129236229000000000" />
<file name="util.php" server="ftp.amarca.net/amarca_management/" local="128765405000000000" remote="129236229000000000" />
<file name="config.php" server="ftp.veacreative.net" local="129350188567656250" remote="129350196000000000" />
<file name="config.php" server="ftp.dicapta.net" local="129350188567656250" remote="129350196600000000" />
</dwsync>